shard_llms/__init__.py
shard_llms/sharding_model.py
utils/__init__.py
utils/read_files.py
shard_llms-0.2.13.dist-info/METADATA
shard_llms-0.2.13.dist-info/WHEEL
shard_llms-0.2.13.dist-info/entry_points.txt
shard_llms-0.2.13.dist-info/top_level.txt
shard_llms-0.2.13.dist-info/RECORD
