Metadata-Version: 2.1
Name: shard-llms
Version: 0.2.13
Summary: Shard Large Language Models
Home-page: https://github.com/yzm1205/Shard-Any-LLMs
Author: Yzm0034
Author-email: yash.mahajan50@gmail.com
Classifier: Programming Language :: Python :: 3
Classifier: License :: OSI Approved :: MIT License
Classifier: Operating System :: OS Independent
Requires-Python: >=3.6
Requires-Dist: transformers
Requires-Dist: torch
